aem_page_verifier/__init__.py
aem_page_verifier/verifier.py
aem_page_verifier-0.1.1.dist-info/licenses/LICENSE
tests/__init__.py
tests/test_verifier.py
aem_page_verifier-0.1.1.dist-info/METADATA
aem_page_verifier-0.1.1.dist-info/WHEEL
aem_page_verifier-0.1.1.dist-info/entry_points.txt
aem_page_verifier-0.1.1.dist-info/top_level.txt
aem_page_verifier-0.1.1.dist-info/RECORD
